n7py/__init__.py
n7py/core.py
n7py/data/1.txt
n7py/data/10.txt
n7py/data/11.txt
n7py/data/12.txt
n7py/data/13.txt
n7py/data/2.txt
n7py/data/3.txt
n7py/data/4.txt
n7py/data/5.txt
n7py/data/6.txt
n7py/data/7.txt
n7py/data/8.txt
n7py/data/9.txt
n7py-3.2.4.dist-info/METADATA
n7py-3.2.4.dist-info/WHEEL
n7py-3.2.4.dist-info/top_level.txt
n7py-3.2.4.dist-info/RECORD
